{
    "check_box": {
        "next": 1640187160,
        "param": {
            "track": true,
            "resize": 0.25
        }
    },
    "heal_500": {
        "next": 1640186594,
        "param": {
            "track": true,
            "resize": 0.25,
            "max_to_heal": 500
        },
        "func": "heal_max"
    },
    "sheltering": {
        "next": 1631940195,
        "param": {
            "track": true,
            "resize": 0.25,
            "reset_threshold": 8
        }
    },
    "trade": {
        "next": 1640186893,
        "param": {
            "track": true,
            "resize": 0.25
        }
    },
    "get_amethyst": {
        "next": 1640190512,
        "param": {
            "track": true,
            "resize": 0.3
        }
    },
    "get_dragonforged": {
        "next": 1640190614,
        "param": {
            "track": true,
            "resize": 0.3
        }
    },
    "get_vip_shop": {
        "next": 1640190688,
        "param": {
            "track": true,
            "resize": 0.3
        }
    },
    "complete_all_trials": {
        "next": 1640154554,
        "param": {
            "track": true,
            "resize": 0.25
        }
    },
    "get_salary": {
        "next": 1640150962,
        "param": {
            "track": true,
            "resize": 0.25
        }
    },
    "get_bonus": {
        "next": 1640150965,
        "param": {
            "track": true,
            "resize": 0.25
        }
    },
    "get_knight": {
        "next": 1640150967,
        "param": {
            "track": true,
            "resize": 0.25
        }
    },
    "get_list": {
        "next": 1640154727,
        "param": {
            "track": true,
            "resize": 0.25,
            "items": [
                "vip",
                "amethyst",
                "dragon"
            ]
        }
    },
    "explore_drag": {
        "next": 1640191084,
        "param": {
            "track": true,
            "resize": 0.25,
            "hours": 1,
            "buy": 0,
            "dragon_id": 0
        }
    },
    "daily_msg": {
        "next": 1640187684,
        "param": {
            "track": true,
            "resize": 0.25
        }
    },
    "sell_quick_box": {
        "next": 1640189784,
        "param": {
            "track": true,
            "resize": 0.25,
            "min_level": 5
        }
    },
    "training_ground": {
        "next": 1640188353,
        "param": {
            "track": true,
            "resize": 0.25
        }
    },
    "soldiers": {
        "cav": 500,
        "inf": 500,
        "spe": 500,
        "bow": 500
    },
    "train_mil": {
        "next": 1640190883,
        "param": {
            "track": true,
            "resize": 0.25,
            "level": 1,
            "soldiers": {
                "cav": 500,
                "inf": 500,
                "spe": 500,
                "bow": 500
            }
        }
    },
    "get_discount": {
        "next": 1640190254,
        "param": {
            "track": true,
            "resize": 0.25
        }
    }
}