{
    "check_box": {
        "next": 1635467760,
        "param": {
            "track": true,
            "resize": 0.25
        }
    },
    "heal_500": {
        "next": 1635467748,
        "param": {
            "track": true,
            "resize": 0.25,
            "max_to_heal": 500
        },
        "func": "heal_max"
    },
    "sheltering": {
        "next": 1631939949,
        "param": {
            "track": true,
            "resize": 0.25,
            "reset_threshold": 8
        }
    },
    "trade": {
        "next": 1635467926,
        "param": {
            "track": true,
            "resize": 0.25
        }
    },
    "get_amethyst": {
        "next": 1635471547,
        "param": {
            "track": true,
            "resize": 0.3
        }
    },
    "get_dragonforged": {
        "next": 1635471624,
        "param": {
            "track": true,
            "resize": 0.3
        }
    },
    "get_vip_shop": {
        "next": 1635471695,
        "param": {
            "track": true,
            "resize": 0.3
        }
    },
    "complete_all_trials": {
        "next": 1635471761,
        "param": {
            "track": true,
            "resize": 0.25
        }
    },
    "get_salary": {
        "next": 1635552614,
        "param": {
            "track": true,
            "resize": 0.25
        }
    },
    "get_bonus": {
        "next": 1635552611,
        "param": {
            "track": true,
            "resize": 0.25
        }
    },
    "get_knight": {
        "next": 1635511634,
        "param": {
            "track": true,
            "resize": 0.25
        }
    },
    "get_list": {
        "next": 1635472066,
        "param": {
            "track": true,
            "resize": 0.25,
            "items": [
                "vip",
                "amethyst",
                "dragon"
            ]
        }
    },
    "explore_drag": {
        "next": 1635453980,
        "param": {
            "track": true,
            "resize": 0.25,
            "hours": 1,
            "buy": 0,
            "dragon_id": 0
        }
    },
    "daily_msg": {
        "next": 1635517757,
        "param": {
            "track": true,
            "resize": 0.25
        }
    },
    "sell_quick_box": {
        "next": 1635456614,
        "param": {
            "track": true,
            "resize": 0.25,
            "min_level": 5
        }
    },
    "training_ground": {
        "next": 1635453816,
        "param": {
            "track": true,
            "resize": 0.25
        }
    }
}