{
    "check_box": {
        "next": 1633343164,
        "param": {
            "track": true,
            "resize": 0.25
        }
    },
    "heal_500": {
        "next": 1633342711,
        "param": {
            "track": true,
            "resize": 0.25,
            "max_to_heal": 500
        },
        "func": "heal_max"
    },
    "sheltering": {
        "next": 1633357331,
        "param": {
            "track": true,
            "resize": 0.25,
            "reset_threshold": 8
        }
    },
    "trade": {
        "next": 1633343157,
        "param": {
            "track": true,
            "resize": 0.25
        }
    },
    "get_amethyst": {
        "next": 1633346771,
        "param": {
            "track": true,
            "resize": 0.3
        }
    },
    "get_dragonforged": {
        "next": 1633324965,
        "param": {
            "track": true,
            "resize": 0.3
        }
    },
    "get_vip_shop": {
        "next": 1633396799,
        "param": {
            "track": true,
            "resize": 0.3
        }
    },
    "training_ground": {
        "next": 1633294106,
        "param": {
            "track": true,
            "resize": 0.25
        }
    },
    "soldiers": {
        "cav": 500,
        "inf": 500,
        "spe": 500,
        "bow": 500
    },
    "train_mil": {
        "next": 1633328961,
        "param": {
            "track": true,
            "resize": 0.25,
            "level": 1,
            "soldiers": {
                "cav": 500,
                "inf": 500,
                "spe": 500,
                "bow": 500
            }
        }
    },
    "explore_drag": {
        "next": 1633329131,
        "param": {
            "track": true,
            "resize": 0.25,
            "hours": 1,
            "buy": 0,
            "dragon_id": 0
        }
    },
    "daily_msg": {
        "next": 1633325727,
        "param": {
            "track": true,
            "resize": 0.25
        }
    },
    "sell_quick_box": {
        "next": 1633329470,
        "param": {
            "track": true,
            "resize": 0.25,
            "min_level": 5
        }
    },
    "complete_all_trials": {
        "next": 1633328727,
        "param": {
            "track": true,
            "resize": 0.25
        }
    },
    "get_salary": {
        "next": 1633325135,
        "param": {
            "track": true,
            "resize": 0.25
        }
    },
    "get_bonus": {
        "next": 1633325138,
        "param": {
            "track": true,
            "resize": 0.25
        }
    },
    "get_knight": {
        "next": 1633325140,
        "param": {
            "track": true,
            "resize": 0.25
        }
    },
    "get_list": {
        "next": 1633328771,
        "param": {
            "track": true,
            "resize": 0.25,
            "items": [
                "vip",
                "amethyst",
                "dragon"
            ]
        }
    }
}