{
    "continue_bub": {
        "next": 1643057037,
        "param": {
            "track": true,
            "resize": 0.25,
            "check_interval": 10800
        }
    },
    "check_box": {
        "next": 1643044850,
        "param": {
            "track": true,
            "resize": 0.25
        }
    },
    "get_discount": {
        "next": 1643045521,
        "param": {
            "track": true,
            "resize": 0.25
        }
    },
    "daily_msg": {
        "next": 1643081709,
        "param": {
            "track": true,
            "resize": 0.25
        }
    }
}