{
    "continue_bub": {
        "next": 1641378018,
        "param": {
            "track": true,
            "resize": 0.25,
            "check_interval": 10800
        }
    },
    "check_box": {
        "next": 1641378573,
        "param": {
            "track": true,
            "resize": 0.25
        }
    },
    "get_discount": {
        "next": 1641381692,
        "param": {
            "track": true,
            "resize": 0.25
        }
    },
    "daily_msg": {
        "next": 1641417888,
        "param": {
            "track": true,
            "resize": 0.25
        }
    },
    "trade": {
        "next": 1641379622,
        "param": {
            "track": true,
            "resize": 0.25
        }
    },
    "get_taven": {
        "next": 1641378552,
        "param": {
            "track": true,
            "resize": 0.25,
            "leave_noclick": 1
        }
    },
    "up_command": {
        "next": 1641382165,
        "param": {
            "name": "russell",
            "step_width": 3,
            "max_try": 6,
            "track": true,
            "resize": 0.25,
            "trigger": 120
        },
        "func": "upgrade_commanders"
    }
}