{
    "continue_bub": {
        "next": 1639154709,
        "param": {
            "track": true,
            "resize": 0.25,
            "check_interval": 10800
        }
    },
    "check_box": {
        "next": 1639148068,
        "param": {
            "track": true,
            "resize": 0.25
        }
    },
    "daily_msg": {
        "next": 1639185427,
        "param": {
            "track": true,
            "resize": 0.25
        }
    },
    "trade": {
        "next": 1639146005,
        "param": {
            "track": true,
            "resize": 0.25
        }
    },
    "get_taven": {
        "next": 1639149584,
        "param": {
            "track": true,
            "resize": 0.25,
            "leave_noclick": 1
        }
    }
}