{
    "continue_bub": {
        "next": 1646186116,
        "param": {
            "track": true,
            "resize": 0.25,
            "check_interval": 10800
        }
    },
    "check_box": {
        "next": 1646173654,
        "param": {
            "track": true,
            "resize": 0.25
        }
    },
    "get_discount": {
        "next": 1646177015,
        "param": {
            "track": true,
            "resize": 0.25
        }
    },
    "daily_msg": {
        "next": 1646213207,
        "param": {
            "track": true,
            "resize": 0.25
        }
    },
    "trade": {
        "next": 1646174938,
        "param": {
            "track": true,
            "resize": 0.25
        }
    },
    "get_taven": {
        "next": 1646173866,
        "param": {
            "track": true,
            "resize": 0.25,
            "leave_noclick": 1
        }
    }
}