{
    "continue_bub": {
        "next": 1655569240,
        "param": {
            "track": true,
            "resize": 0.25
        },
        "local": "06/18/2022 10:20:40"
    },
    "check_box": {
        "next": 1655564163,
        "param": {
            "track": true,
            "resize": 0.25
        },
        "local": "06/18/2022 08:56:03"
    },
    "get_discount": {
        "next": 1655564917,
        "param": {
            "track": true,
            "resize": 0.25
        },
        "local": "06/18/2022 09:08:37"
    },
    "trade": {
        "next": 1655575644,
        "param": {
            "track": true,
            "resize": 0.25
        },
        "local": "06/18/2022 12:07:24"
    },
    "get_salary": {
        "next": 1655597403,
        "param": {
            "track": true,
            "resize": 0.25
        },
        "local": "06/18/2022 18:10:03"
    },
    "get_bonus": {
        "next": 1655597402,
        "param": {
            "track": true,
            "resize": 0.25
        },
        "local": "06/18/2022 18:10:02"
    },
    "get_knight": {
        "next": 1655597399,
        "param": {
            "track": true,
            "resize": 0.25
        },
        "local": "06/18/2022 18:09:59"
    },
    "get_amethyst": {
        "next": 1655601599,
        "param": {
            "track": true,
            "resize": 0.3
        },
        "local": "06/18/2022 19:19:59"
    },
    "get_taven": {
        "next": 1655565110,
        "param": {
            "track": true,
            "resize": 0.25,
            "leave_noclick": 1
        },
        "local": "06/18/2022 09:11:50"
    },
    "get_alli_quest": {
        "next": 1655576623,
        "param": {
            "track": true,
            "resize": 0.25
        },
        "local": "06/18/2022 12:23:43"
    },
    "sell_quick_box": {
        "next": 1655597194,
        "param": {
            "track": true,
            "resize": 0.25,
            "min_level": 12
        },
        "local": "06/18/2022 18:06:34"
    },
    "explore_drag": {
        "next": 1655565536,
        "param": {
            "track": true,
            "resize": 0.25,
            "hours": 1,
            "buy": 0,
            "dragon_id": 1
        },
        "local": "06/18/2022 09:18:56"
    },
    "get_vip_box": {
        "next": 1655601599,
        "param": {
            "track": true,
            "resize": 0.25
        },
        "local": "06/18/2022 19:19:59"
    },
    "schedule_leader": {
        "next": 1655566446,
        "param": {
            "side": "right",
            "level": 4,
            "track": true,
            "resize": 0.25,
            "hits": 5,
            "cost": 1682,
            "toadd_motiv": 0
        },
        "local": "06/18/2022 09:34:06"
    },
    "get_active_award": {
        "next": 1655564744,
        "local": "06/18/2022 09:05:44"
    },
    "auto_transport_rss": {
        "next": 1655564812,
        "local": "06/18/2022 09:06:52"
    },
    "get_alliance_chests": {
        "next": 1655571164,
        "local": "06/18/2022 10:52:44"
    },
    "bliz_elite_trial": {
        "next": 1655630264,
        "local": "06/19/2022 03:17:44"
    },
    "daily_msg": {
        "next": 1655597555,
        "local": "06/18/2022 18:12:35"
    },
    "upgrade_commanders": {
        "next": 1655565904,
        "local": "06/18/2022 09:25:04"
    },
    "expeditions": {
        "next": 1655565151,
        "local": "06/18/2022 09:12:31"
    },
    "training_ground": {
        "next": 1655599668,
        "local": "06/18/2022 18:47:48"
    },
    "daily_train": {
        "next": 1655565200,
        "local": "06/18/2022 09:13:20"
    },
    "at_groups": {
        "next": 1655566814,
        "local": "06/18/2022 09:40:14"
    },
    "bank_claim": {
        "next": 1655565229,
        "local": "06/18/2022 09:13:49"
    },
    "balanced_farms": {
        "next": 1655563641,
        "local": "06/18/2022 08:47:21"
    },
    "check_midsummer": {
        "next": 1655565062,
        "local": "06/18/2022 09:11:02"
    },
    "enter_code": {
        "next": 1655564311,
        "local": "06/18/2022 08:58:31"
    }
}